prompt_gen/__init__.py
prompt_gen/about.py
prompt_gen/generator.py
prompt_gen/util.py
prompt_gen/character_data/__init__.py
prompt_gen/location_data/__init__.py
prompt_gen/scenario_data/__init__.py
prompt_gen-0.0.3.dist-info/LICENSE
prompt_gen-0.0.3.dist-info/METADATA
prompt_gen-0.0.3.dist-info/WHEEL
prompt_gen-0.0.3.dist-info/top_level.txt
prompt_gen-0.0.3.dist-info/zip-safe
prompt_gen-0.0.3.dist-info/RECORD
