Metadata-Version: 2.1
Name: prompt-gen
Version: 0.0.3
Summary: A lightweight prompt generator for Python. Primarily for text to image synthesis.
Home-page: https://github.com/Just-Understanding-Data-Ltd/promp_gen
Author: James Antony Phoenix
Author-email: jamesaphoenix@googlemail.com
License: MIT
Keywords: prompt,generator,prompt_gen,ai_art,art,dalle,dalle2,midjourney,dalle3
License-File: LICENSE
Requires-Dist: numpy
Requires-Dist: pandas
